BDL/ByteDarkLock.py
BDL/__init__.py
utils/__init__.py
utils/helpers.py
bytedarklock-1.0.0.dist-info/LICENSE
bytedarklock-1.0.0.dist-info/METADATA
bytedarklock-1.0.0.dist-info/WHEEL
bytedarklock-1.0.0.dist-info/top_level.txt
bytedarklock-1.0.0.dist-info/RECORD
