Metadata-Version: 2.2
Name: ByteDarkLock
Version: 1.0.0
Summary: Symmetric encryption and code obfuscation utilities (ByteDarkLock).
Home-page: https://github.com/FakeFountain548/ByteDarkLocker-BDL
Author: FakeFountain548
Author-email: gaelsolanoespinosa@gmail.com
Classifier: Programming Language :: Python :: 3
Classifier: License :: OSI Approved :: MIT License
Classifier: Operating System :: OS Independent
Requires-Python: >=3.6
License-File: LICENSE
Requires-Dist: cryptography>=3.4.7
Requires-Dist: Pillow>=8.1.0
Dynamic: author
Dynamic: author-email
Dynamic: classifier
Dynamic: description
Dynamic: description-content-type
Dynamic: home-page
Dynamic: requires-dist
Dynamic: requires-python
Dynamic: summary
